{"name": "GEOFON", "website": "https://data.center.org/", "fullName": "GEOFON Data Centre", "summary": "One-liner presenting the data center", "repositories": [{"name": "archive", "description": "Archive of continuous seismological data", "website": "https://data.center.org/waveform/", "services": [{"name": "fdsnws-dataselect-1", "description": "Access to raw time series data", "url": "https://geofon.gfz-potsdam.de/fdsnws/dataselect/1/"}, {"name": "fdsnws-station-1", "description": "Access to metadata describing raw time series data", "url": "https://geofon.gfz-potsdam.de/fdsnws/station/1/"}, {"name": "fdsnws-availability-1", "description": "Access to the availability of the time series data", "url": "https://geofon.gfz-potsdam.de/fdsnws/availability/1/"}, {"name": "eidaws-wfcatalog", "description": "EIDA WFCatalog service", "url": "https://geofon.gfz-potsdam.de/eidaws/wfcatalog/1/"}], "datasets": []}]}